identtqueue/__init__.py
identtqueue/client.py
identtqueue/exceptions.py
identtqueue/job.py
identtqueue/utils.py
identtqueue/worker.py
identtqueue-0.2.2.dist-info/LICENSE
identtqueue-0.2.2.dist-info/METADATA
identtqueue-0.2.2.dist-info/WHEEL
identtqueue-0.2.2.dist-info/top_level.txt
identtqueue-0.2.2.dist-info/RECORD
