Metadata-Version: 2.1
Name: identtqueue
Version: 0.2.2
Summary: Task queue package
Home-page: UNKNOWN
Author: Piotr Giedziun
Author-email: piotr.giedziun@identt.pl
License: MIT license
Keywords: identtqueue
Platform: UNKNOWN
Classifier: License :: OSI Approved :: MIT License
Classifier: Natural Language :: English
Classifier: Programming Language :: Python :: 3
Classifier: Programming Language :: Python :: 3.6
Classifier: Programming Language :: Python :: 3.7
Classifier: Programming Language :: Python :: 3.8
Requires-Python: >=3.6
License-File: LICENSE
Requires-Dist: aioredis (~=2.0.0)
Requires-Dist: structlog (~=21.1.0)
Requires-Dist: msgpack (~=1.0.2)
